{
    "@context": [
        "https://doi.org/10.5063/schema/codemeta-2.0",
        "https://w3id.org/software-iodata",
        "https://raw.githubusercontent.com/jantman/repostatus.org/master/badges/latest/ontology.jsonld",
        "https://schema.org",
        "https://w3id.org/software-types"
    ],
    "@type": "SoftwareSourceCode",
    "codeRepository": "https://github.com/CLARIAH/burgerLinker.git",
    "contributor": [
        {
            "@type": "Person",
            "email": "richard.zijdeman@iisg.nl",
            "familyName": "Zijdeman",
            "givenName": "Richard"
        },
        {
            "@type": "Person",
            "email": "raad.joe@hotmail.com",
            "familyName": "Raad",
            "givenName": "Joe"
        },
        {
            "@type": "Person",
            "email": "rick.mourits@iisg.nl",
            "familyName": "Mourits",
            "givenName": "Rick"
        },
        {
            "@type": "Person",
            "email": "rubenschalk1@gmail.com",
            "familyName": "Schalk",
            "givenName": "Ruben"
        }
    ],
    "dateCreated": "2021-02-16T13:19:31Z+0100",
    "dateModified": "2022-09-21T11:03:01Z+0200",
    "description": "Command line tool for linking civil registries",
    "developmentStatus": "https://www.repostatus.org/#inactive",
    "identifier": "burgerLinker",
    "funding": {
        "@type": "Grant",
        "name": "CLARIAH-PLUS (NWO grant 184.034.023)",
        "funder": {
            "@type": "Organization",
            "name": "NWO", 
            "url": "https://www.nwo.nl"
        }
    },
    "referencePublication": { 
           "@type": "ScholarlyArticle",
           "url": "https://ceur-ws.org/Vol-2695/paper6.pdf"
    },
    "issueTracker": "https://github.com/CLARIAH/burgerLinker/issues",
    "license": "http://spdx.org/licenses/MIT",
    "name": "burgerLinker",
    "producer": {
        "@type": "Organization",
        "name": "CLARIAH",
        "url": "http://www.clariah.nl"
    },
    "programmingLanguage": "Java",
    "readme": "https://github.com/CLARIAH/burgerLinker/blob//README.md",
    "runtimePlatform": "Java",
    "softwareRequirements": [
        {
            "@type": "SoftwareApplication",
            "identifier": "org.rdfhdt.hdt-java-core",
            "name": "hdt-java-core",
            "version": "3.0.2"
        },
        {
            "@type": "SoftwareApplication",
            "identifier": "org.rdfhdt.hdt-jena",
            "name": "hdt-jena",
            "version": "3.0.2"
        },
        {
            "@type": "SoftwareApplication",
            "identifier": "com.beust.jcommander",
            "name": "jcommander",
            "version": "1.78"
        },
        {
            "@type": "SoftwareApplication",
            "identifier": "junit.junit",
            "name": "junit",
            "version": "3.8.1"
        },
        {
            "@type": "SoftwareApplication",
            "identifier": "com.github.universal-automata.liblevenshtein",
            "name": "liblevenshtein",
            "version": "3.0.0"
        },
        {
            "@type": "SoftwareApplication",
            "identifier": "org.apache.logging.log4j.log4j-core",
            "name": "log4j-core",
            "version": "2.17.2"
        },
        {
            "@type": "SoftwareApplication",
            "identifier": "com.opencsv.opencsv",
            "name": "opencsv",
            "version": "5.2"
        },
        {
            "@type": "SoftwareApplication",
            "identifier": "me.tongfei.progressbar",
            "name": "progressbar",
            "version": "0.8.1"
        },
        {
            "@type": "SoftwareApplication",
            "identifier": "org.rocksdb.rocksdbjni",
            "name": "rocksdbjni",
            "version": "6.12.7"
        },
        {
            "@type": "SoftwareApplication",
            "identifier": "org.slf4j.slf4j-api",
            "name": "slf4j-api",
            "version": "1.7.5"
        },
        {
            "@type": "SoftwareApplication",
            "identifier": "org.slf4j.slf4j-log4j12",
            "name": "slf4j-log4j12",
            "version": "1.7.5"
        }
    ],
    "targetProduct": {
        "@type": "CommandLineApplication",
        "name": "burgerLinker"
    },
    "version": "0.0.1-SNAPSHOT"
}
